optimeering/__init__.py
optimeering/api_client.py
optimeering/api_response.py
optimeering/azure_authentication.py
optimeering/configuration.py
optimeering/exceptions.py
optimeering/extras.py
optimeering/logger.py
optimeering/rest.py
optimeering/silent_type_cast.py
optimeering/api/__init__.py
optimeering/api/access_api.py
optimeering/api/predictions_api.py
optimeering/models/__init__.py
optimeering/models/access_key_created.py
optimeering/models/access_key_list_key_response.py
optimeering/models/access_key_post_response.py
optimeering/models/access_post_key.py
optimeering/models/event_time_end.py
optimeering/models/event_time_start.py
optimeering/models/expires_at.py
optimeering/models/http_validation_error.py
optimeering/models/max_event_time.py
optimeering/models/predictions_data.py
optimeering/models/predictions_data_list.py
optimeering/models/predictions_event.py
optimeering/models/predictions_series.py
optimeering/models/predictions_series_list.py
optimeering/models/predictions_value.py
optimeering/models/predictions_version.py
optimeering/models/predictions_version_list.py
optimeering/models/validation_error.py
optimeering/models/validation_error_loc_inner.py
optimeering/models/versioned_series.py
optimeering-0.0.6.dist-info/METADATA
optimeering-0.0.6.dist-info/WHEEL
optimeering-0.0.6.dist-info/namespace_packages.txt
optimeering-0.0.6.dist-info/top_level.txt
optimeering-0.0.6.dist-info/RECORD
