Metadata-Version: 2.4
Name: optimeering
Version: 0.0.6
Summary: Optimeering Python Client
Author: Optimeering
Classifier: Programming Language :: Python :: 3.10
Classifier: Programming Language :: Python :: 3.11
Requires-Python: <4.0,>=3.11
Requires-Dist: azure-identity<2.0.0,>=1.17.1
Requires-Dist: orjson<4.0.0,>=3.10.15
Requires-Dist: pydantic>=2
Requires-Dist: python-dateutil>=2.8.2
Requires-Dist: types-python-dateutil>=2.8.19.14
Requires-Dist: typing-extensions>=4.7.1
Requires-Dist: urllib3>=1.25.3
Dynamic: author
Dynamic: classifier
Dynamic: description
Dynamic: description-content-type
Dynamic: requires-dist
Dynamic: requires-python
Dynamic: summary
